hack4u/__init__.py
hack4u/courses.py
hack4u/utils.py
daryl_test-0.1.0.dist-info/METADATA
daryl_test-0.1.0.dist-info/WHEEL
daryl_test-0.1.0.dist-info/top_level.txt
daryl_test-0.1.0.dist-info/RECORD
