Metadata-Version: 2.2
Name: daryl_test
Version: 0.1.0
Summary: Una biblioteca para consultar cursos de hack4u.
Home-page: https://hack4u.io/
Author: Daryl Esquivel
Dynamic: author
Dynamic: description-content-type
Dynamic: home-page
Dynamic: summary
